Workbook

Sheet Apartment Tracker
A1: Monthly budget limit (₹) | B1: 30000 | C1: Total monthly cost turns red above this limit. Change the number in B1 any time.
A2: Society / building name | B2: Location / area | C2: Apartment type | D2: Status | E2: Broker name | F2: Broker contact | G2: Rent (₹/month) | H2: Maintenance (₹/month) | I2: Total monthly cost (₹) | J2: Deposit (₹) | K2: Brokerage fee (₹) | L2: Area (sq ft) | M2: Floor / total floors | N2: Furnishing | O2: Parking | P2: Lift | Q2: Available from | R2: Distance from workplace (km) | S2: Safety (1-5) | T2: Water supply (1-5) | U2: Location (1-5) | V2: Condition (1-5) | W2: Natural light (1-5) | X2: Overall rating (1-5) | Y2: Pros | Z2: Cons | AA2: Photos link | AB2: Shortlist # (auto)
A3: Kavisha AER | B3: Shela | C3: 2BHK | D3: To call | E3: Sunil Rathore | F3: 6352591294 | G3: 23000 | H3: 0 | I3: =IF(COUNT(G3:H3)=0,"",SUM(G3:H3)) -> 23000 | N3: Semi-furnished | O3: Yes | P3: Yes | X3: =IF(COUNT(S3:W3)=0,"",AVERAGE(S3:W3)) | Y3: Price is negotiable; closer to office; prime location | AB3: =IF(D3="Shortlisted",COUNTIF(D$3:D3,"Shortlisted"),"")
A4: Samyaka Apartment | B4: Vejalpur | C4: 2BHK | D4: To call | E4: Sunil Rathore | F4: 6352591294 | G4: 30000 | I4: =IF(COUNT(G4:H4)=0,"",SUM(G4:H4)) -> 30000 | N4: Fully furnished | X4: =IF(COUNT(S4:W4)=0,"",AVERAGE(S4:W4)) | Z4: No pets allowed; only family allowed | AB4: =IF(D4="Shortlisted",COUNTIF(D$3:D4,"Shortlisted"),"")
A5: To ask | B5: Vejalpur | C5: 2BHK | D5: To call | E5: Sunil Rathore | F5: 6352591294 | G5: 30000 | I5: =IF(COUNT(G5:H5)=0,"",SUM(G5:H5)) -> 30000 | N5: Fully furnished | O5: Yes | P5: Yes | Q5: 20th October | X5: =IF(COUNT(S5:W5)=0,"",AVERAGE(S5:W5)) | AB5: =IF(D5="Shortlisted",COUNTIF(D$3:D5,"Shortlisted"),"")
A6: Turquoise Blu | B6: Shela | C6: 2BHK | D6: To call | E6: Sunil Rathore | F6: 6352591294 | G6: 35000 | I6: =IF(COUNT(G6:H6)=0,"",SUM(G6:H6)) -> 35000 | N6: Fully furnished | O6: Yes | P6: Yes | X6: =IF(COUNT(S6:W6)=0,"",AVERAGE(S6:W6)) | Y6: Gym; Garden; Grocery store below | Z6: Expensive | AB6: =IF(D6="Shortlisted",COUNTIF(D$3:D6,"Shortlisted"),"")
A7: To ask | D7: To call | E7: Kameshwar | F7: 9033096145 | I7: =IF(COUNT(G7:H7)=0,"",SUM(G7:H7)) | X7: =IF(COUNT(S7:W7)=0,"",AVERAGE(S7:W7)) | AB7: =IF(D7="Shortlisted",COUNTIF(D$3:D7,"Shortlisted"),"")
A8: AARYAN GLORIA | B8: South Bhopal | C8: 3BHK | D8: To call | E8: RB Realty Solutions | F8: 9925646455 | G8: 29000 | I8: =IF(COUNT(G8:H8)=0,"",SUM(G8:H8)) -> 29000 | N8: Semi-furnished | X8: =IF(COUNT(S8:W8)=0,"",AVERAGE(S8:W8)) | Y8: Price is negotiable | AB8: =IF(D8="Shortlisted",COUNTIF(D$3:D8,"Shortlisted"),"")
A9: To ask | D9: To call | E9: Ganatra Kamlesh Narbheram | F9: 7984369394 | I9: =IF(COUNT(G9:H9)=0,"",SUM(G9:H9)) | X9: =IF(COUNT(S9:W9)=0,"",AVERAGE(S9:W9)) | AB9: =IF(D9="Shortlisted",COUNTIF(D$3:D9,"Shortlisted"),"")
A10: To ask | D10: To call | E10: Hardik Bhupendrabhai | F10: 8128713336 | I10: =IF(COUNT(G10:H10)=0,"",SUM(G10:H10)) | X10: =IF(COUNT(S10:W10)=0,"",AVERAGE(S10:W10)) | AB10: =IF(D10="Shortlisted",COUNTIF(D$3:D10,"Shortlisted"),"")
A11: To ask | D11: To call | E11: Dilip Patel | F11: 8320987782 | I11: =IF(COUNT(G11:H11)=0,"",SUM(G11:H11)) | X11: =IF(COUNT(S11:W11)=0,"",AVERAGE(S11:W11)) | AB11: =IF(D11="Shortlisted",COUNTIF(D$3:D11,"Shortlisted"),"")
A12: To ask | D12: To call | E12: Mansi Bodakdev | F12: 9712394555 | I12: =IF(COUNT(G12:H12)=0,"",SUM(G12:H12)) | X12: =IF(COUNT(S12:W12)=0,"",AVERAGE(S12:W12)) | AB12: =IF(D12="Shortlisted",COUNTIF(D$3:D12,"Shortlisted"),"")
A13: Maher 5 | B13: Shela | C13: 2BHK | D13: To call | E13: RB Realtors | F13: 9925579097 | G13: 22000 | I13: =IF(COUNT(G13:H13)=0,"",SUM(G13:H13)) -> 22000 | N13: Semi-furnished | O13: Yes | P13: Yes | X13: =IF(COUNT(S13:W13)=0,"",AVERAGE(S13:W13)) | AB13: =IF(D13="Shortlisted",COUNTIF(D$3:D13,"Shortlisted"),"")
I14: =IF(COUNT(G14:H14)=0,"",SUM(G14:H14)) | X14: =IF(COUNT(S14:W14)=0,"",AVERAGE(S14:W14)) | AB14: =IF(D14="Shortlisted",COUNTIF(D$3:D14,"Shortlisted"),"")
I15: =IF(COUNT(G15:H15)=0,"",SUM(G15:H15)) | X15: =IF(COUNT(S15:W15)=0,"",AVERAGE(S15:W15)) | AB15: =IF(D15="Shortlisted",COUNTIF(D$3:D15,"Shortlisted"),"")
I16: =IF(COUNT(G16:H16)=0,"",SUM(G16:H16)) | X16: =IF(COUNT(S16:W16)=0,"",AVERAGE(S16:W16)) | AB16: =IF(D16="Shortlisted",COUNTIF(D$3:D16,"Shortlisted"),"")
A17: North Enclave | B17: Vaishnodevi | C17: 2BHK | G17: 23000 | I17: =IF(COUNT(G17:H17)=0,"",SUM(G17:H17)) -> 23000 | J17: 46000 | N17: Semi-furnished | O17: Yes | P17: Yes | X17: =IF(COUNT(S17:W17)=0,"",AVERAGE(S17:W17)) | Y17: 2 balconies, higher floor, good view | AB17: =IF(D17="Shortlisted",COUNTIF(D$3:D17,"Shortlisted"),"")
A18: Suryansh Sanidhya Shivalaya | I18: =IF(COUNT(G18:H18)=0,"",SUM(G18:H18)) | X18: =IF(COUNT(S18:W18)=0,"",AVERAGE(S18:W18)) | Z18: Too far | AB18: =IF(D18="Shortlisted",COUNTIF(D$3:D18,"Shortlisted"),"")
I19: =IF(COUNT(G19:H19)=0,"",SUM(G19:H19)) | X19: =IF(COUNT(S19:W19)=0,"",AVERAGE(S19:W19)) | AB19: =IF(D19="Shortlisted",COUNTIF(D$3:D19,"Shortlisted"),"")
I20: =IF(COUNT(G20:H20)=0,"",SUM(G20:H20)) | X20: =IF(COUNT(S20:W20)=0,"",AVERAGE(S20:W20)) | AB20: =IF(D20="Shortlisted",COUNTIF(D$3:D20,"Shortlisted"),"")
I21: =IF(COUNT(G21:H21)=0,"",SUM(G21:H21)) | X21: =IF(COUNT(S21:W21)=0,"",AVERAGE(S21:W21)) | AB21: =IF(D21="Shortlisted",COUNTIF(D$3:D21,"Shortlisted"),"")
I22: =IF(COUNT(G22:H22)=0,"",SUM(G22:H22)) | X22: =IF(COUNT(S22:W22)=0,"",AVERAGE(S22:W22)) | AB22: =IF(D22="Shortlisted",COUNTIF(D$3:D22,"Shortlisted"),"")
I23: =IF(COUNT(G23:H23)=0,"",SUM(G23:H23)) | X23: =IF(COUNT(S23:W23)=0,"",AVERAGE(S23:W23)) | AB23: =IF(D23="Shortlisted",COUNTIF(D$3:D23,"Shortlisted"),"")
I24: =IF(COUNT(G24:H24)=0,"",SUM(G24:H24)) | X24: =IF(COUNT(S24:W24)=0,"",AVERAGE(S24:W24)) | AB24: =IF(D24="Shortlisted",COUNTIF(D$3:D24,"Shortlisted"),"")
I25: =IF(COUNT(G25:H25)=0,"",SUM(G25:H25)) | X25: =IF(COUNT(S25:W25)=0,"",AVERAGE(S25:W25)) | AB25: =IF(D25="Shortlisted",COUNTIF(D$3:D25,"Shortlisted"),"")
I26: =IF(COUNT(G26:H26)=0,"",SUM(G26:H26)) | X26: =IF(COUNT(S26:W26)=0,"",AVERAGE(S26:W26)) | AB26: =IF(D26="Shortlisted",COUNTIF(D$3:D26,"Shortlisted"),"")
I27: =IF(COUNT(G27:H27)=0,"",SUM(G27:H27)) | X27: =IF(COUNT(S27:W27)=0,"",AVERAGE(S27:W27)) | AB27: =IF(D27="Shortlisted",COUNTIF(D$3:D27,"Shortlisted"),"")
I28: =IF(COUNT(G28:H28)=0,"",SUM(G28:H28)) | X28: =IF(COUNT(S28:W28)=0,"",AVERAGE(S28:W28)) | AB28: =IF(D28="Shortlisted",COUNTIF(D$3:D28,"Shortlisted"),"")
I29: =IF(COUNT(G29:H29)=0,"",SUM(G29:H29)) | X29: =IF(COUNT(S29:W29)=0,"",AVERAGE(S29:W29)) | AB29: =IF(D29="Shortlisted",COUNTIF(D$3:D29,"Shortlisted"),"")
I30: =IF(COUNT(G30:H30)=0,"",SUM(G30:H30)) | X30: =IF(COUNT(S30:W30)=0,"",AVERAGE(S30:W30)) | AB30: =IF(D30="Shortlisted",COUNTIF(D$3:D30,"Shortlisted"),"")
... I62: =IF(COUNT(G62:H62)=0,"",SUM(G62:H62)) | X62: =IF(COUNT(S62:W62)=0,"",AVERAGE(S62:W62)) | AB62: =IF(D62="Shortlisted",COUNTIF(D$3:D62,"Shortlisted"),"")

Sheet Shortlist Comparison
A1: Shortlisted apartments | B1: 1 | C1: 2 | D1: 3 | E1: 4 | F1: 5 | G1: 6 | H1: 7 | I1: 8
A2: Row in tracker (auto) | B2: =IFERROR(MATCH(B$1,'Apartment Tracker'!$AB$3:$AB$62,0),"") | C2: =IFERROR(MATCH(C$1,'Apartment Tracker'!$AB$3:$AB$62,0),"") | D2: =IFERROR(MATCH(D$1,'Apartment Tracker'!$AB$3:$AB$62,0),"") | E2: =IFERROR(MATCH(E$1,'Apartment Tracker'!$AB$3:$AB$62,0),"") | F2: =IFERROR(MATCH(F$1,'Apartment Tracker'!$AB$3:$AB$62,0),"") | G2: =IFERROR(MATCH(G$1,'Apartment Tracker'!$AB$3:$AB$62,0),"") | H2: =IFERROR(MATCH(H$1,'Apartment Tracker'!$AB$3:$AB$62,0),"") | I2: =IFERROR(MATCH(I$1,'Apartment Tracker'!$AB$3:$AB$62,0),"")
A3: Society / building name | B3: {=IF(B$2="","",IF(INDEX('Apartment Tracker'!$A$3:$A$62,B$2)="","",INDEX('Apartment Tracker'!$A$3:$A$62,B$2)))} | C3: {=IF(C$2="","",IF(INDEX('Apartment Tracker'!$A$3:$A$62,C$2)="","",INDEX('Apartment Tracker'!$A$3:$A$62,C$2)))} | D3: {=IF(D$2="","",IF(INDEX('Apartment Tracker'!$A$3:$A$62,D$2)="","",INDEX('Apartment Tracker'!$A$3:$A$62,D$2)))} | E3: {=IF(E$2="","",IF(INDEX('Apartment Tracker'!$A$3:$A$62,E$2)="","",INDEX('Apartment Tracker'!$A$3:$A$62,E$2)))} | F3: {=IF(F$2="","",IF(INDEX('Apartment Tracker'!$A$3:$A$62,F$2)="","",INDEX('Apartment Tracker'!$A$3:$A$62,F$2)))} | G3: {=IF(G$2="","",IF(INDEX('Apartment Tracker'!$A$3:$A$62,G$2)="","",INDEX('Apartment Tracker'!$A$3:$A$62,G$2)))} | H3: {=IF(H$2="","",IF(INDEX('Apartment Tracker'!$A$3:$A$62,H$2)="","",INDEX('Apartment Tracker'!$A$3:$A$62,H$2)))} | I3: {=IF(I$2="","",IF(INDEX('Apartment Tracker'!$A$3:$A$62,I$2)="","",INDEX('Apartment Tracker'!$A$3:$A$62,I$2)))}
A4: Location / area | B4: {=IF(B$2="","",IF(INDEX('Apartment Tracker'!$B$3:$B$62,B$2)="","",INDEX('Apartment Tracker'!$B$3:$B$62,B$2)))} | C4: {=IF(C$2="","",IF(INDEX('Apartment Tracker'!$B$3:$B$62,C$2)="","",INDEX('Apartment Tracker'!$B$3:$B$62,C$2)))} | D4: {=IF(D$2="","",IF(INDEX('Apartment Tracker'!$B$3:$B$62,D$2)="","",INDEX('Apartment Tracker'!$B$3:$B$62,D$2)))} | E4: {=IF(E$2="","",IF(INDEX('Apartment Tracker'!$B$3:$B$62,E$2)="","",INDEX('Apartment Tracker'!$B$3:$B$62,E$2)))} | F4: {=IF(F$2="","",IF(INDEX('Apartment Tracker'!$B$3:$B$62,F$2)="","",INDEX('Apartment Tracker'!$B$3:$B$62,F$2)))} | G4: {=IF(G$2="","",IF(INDEX('Apartment Tracker'!$B$3:$B$62,G$2)="","",INDEX('Apartment Tracker'!$B$3:$B$62,G$2)))} | H4: {=IF(H$2="","",IF(INDEX('Apartment Tracker'!$B$3:$B$62,H$2)="","",INDEX('Apartment Tracker'!$B$3:$B$62,H$2)))} | I4: {=IF(I$2="","",IF(INDEX('Apartment Tracker'!$B$3:$B$62,I$2)="","",INDEX('Apartment Tracker'!$B$3:$B$62,I$2)))}
A5: Apartment type | B5: {=IF(B$2="","",IF(INDEX('Apartment Tracker'!$C$3:$C$62,B$2)="","",INDEX('Apartment Tracker'!$C$3:$C$62,B$2)))} | C5: {=IF(C$2="","",IF(INDEX('Apartment Tracker'!$C$3:$C$62,C$2)="","",INDEX('Apartment Tracker'!$C$3:$C$62,C$2)))} | D5: {=IF(D$2="","",IF(INDEX('Apartment Tracker'!$C$3:$C$62,D$2)="","",INDEX('Apartment Tracker'!$C$3:$C$62,D$2)))} | E5: {=IF(E$2="","",IF(INDEX('Apartment Tracker'!$C$3:$C$62,E$2)="","",INDEX('Apartment Tracker'!$C$3:$C$62,E$2)))} | F5: {=IF(F$2="","",IF(INDEX('Apartment Tracker'!$C$3:$C$62,F$2)="","",INDEX('Apartment Tracker'!$C$3:$C$62,F$2)))} | G5: {=IF(G$2="","",IF(INDEX('Apartment Tracker'!$C$3:$C$62,G$2)="","",INDEX('Apartment Tracker'!$C$3:$C$62,G$2)))} | H5: {=IF(H$2="","",IF(INDEX('Apartment Tracker'!$C$3:$C$62,H$2)="","",INDEX('Apartment Tracker'!$C$3:$C$62,H$2)))} | I5: {=IF(I$2="","",IF(INDEX('Apartment Tracker'!$C$3:$C$62,I$2)="","",INDEX('Apartment Tracker'!$C$3:$C$62,I$2)))}
A6: Broker name | B6: {=IF(B$2="","",IF(INDEX('Apartment Tracker'!$E$3:$E$62,B$2)="","",INDEX('Apartment Tracker'!$E$3:$E$62,B$2)))} | C6: {=IF(C$2="","",IF(INDEX('Apartment Tracker'!$E$3:$E$62,C$2)="","",INDEX('Apartment Tracker'!$E$3:$E$62,C$2)))} | D6: {=IF(D$2="","",IF(INDEX('Apartment Tracker'!$E$3:$E$62,D$2)="","",INDEX('Apartment Tracker'!$E$3:$E$62,D$2)))} | E6: {=IF(E$2="","",IF(INDEX('Apartment Tracker'!$E$3:$E$62,E$2)="","",INDEX('Apartment Tracker'!$E$3:$E$62,E$2)))} | F6: {=IF(F$2="","",IF(INDEX('Apartment Tracker'!$E$3:$E$62,F$2)="","",INDEX('Apartment Tracker'!$E$3:$E$62,F$2)))} | G6: {=IF(G$2="","",IF(INDEX('Apartment Tracker'!$E$3:$E$62,G$2)="","",INDEX('Apartment Tracker'!$E$3:$E$62,G$2)))} | H6: {=IF(H$2="","",IF(INDEX('Apartment Tracker'!$E$3:$E$62,H$2)="","",INDEX('Apartment Tracker'!$E$3:$E$62,H$2)))} | I6: {=IF(I$2="","",IF(INDEX('Apartment Tracker'!$E$3:$E$62,I$2)="","",INDEX('Apartment Tracker'!$E$3:$E$62,I$2)))}
A7: Broker contact | B7: {=IF(B$2="","",IF(INDEX('Apartment Tracker'!$F$3:$F$62,B$2)="","",INDEX('Apartment Tracker'!$F$3:$F$62,B$2)))} | C7: {=IF(C$2="","",IF(INDEX('Apartment Tracker'!$F$3:$F$62,C$2)="","",INDEX('Apartment Tracker'!$F$3:$F$62,C$2)))} | D7: {=IF(D$2="","",IF(INDEX('Apartment Tracker'!$F$3:$F$62,D$2)="","",INDEX('Apartment Tracker'!$F$3:$F$62,D$2)))} | E7: {=IF(E$2="","",IF(INDEX('Apartment Tracker'!$F$3:$F$62,E$2)="","",INDEX('Apartment Tracker'!$F$3:$F$62,E$2)))} | F7: {=IF(F$2="","",IF(INDEX('Apartment Tracker'!$F$3:$F$62,F$2)="","",INDEX('Apartment Tracker'!$F$3:$F$62,F$2)))} | G7: {=IF(G$2="","",IF(INDEX('Apartment Tracker'!$F$3:$F$62,G$2)="","",INDEX('Apartment Tracker'!$F$3:$F$62,G$2)))} | H7: {=IF(H$2="","",IF(INDEX('Apartment Tracker'!$F$3:$F$62,H$2)="","",INDEX('Apartment Tracker'!$F$3:$F$62,H$2)))} | I7: {=IF(I$2="","",IF(INDEX('Apartment Tracker'!$F$3:$F$62,I$2)="","",INDEX('Apartment Tracker'!$F$3:$F$62,I$2)))}
A8: Rent (₹/month) | B8: {=IF(B$2="","",IF(INDEX('Apartment Tracker'!$G$3:$G$62,B$2)="","",INDEX('Apartment Tracker'!$G$3:$G$62,B$2)))} | C8: {=IF(C$2="","",IF(INDEX('Apartment Tracker'!$G$3:$G$62,C$2)="","",INDEX('Apartment Tracker'!$G$3:$G$62,C$2)))} | D8: {=IF(D$2="","",IF(INDEX('Apartment Tracker'!$G$3:$G$62,D$2)="","",INDEX('Apartment Tracker'!$G$3:$G$62,D$2)))} | E8: {=IF(E$2="","",IF(INDEX('Apartment Tracker'!$G$3:$G$62,E$2)="","",INDEX('Apartment Tracker'!$G$3:$G$62,E$2)))} | F8: {=IF(F$2="","",IF(INDEX('Apartment Tracker'!$G$3:$G$62,F$2)="","",INDEX('Apartment Tracker'!$G$3:$G$62,F$2)))} | G8: {=IF(G$2="","",IF(INDEX('Apartment Tracker'!$G$3:$G$62,G$2)="","",INDEX('Apartment Tracker'!$G$3:$G$62,G$2)))} | H8: {=IF(H$2="","",IF(INDEX('Apartment Tracker'!$G$3:$G$62,H$2)="","",INDEX('Apartment Tracker'!$G$3:$G$62,H$2)))} | I8: {=IF(I$2="","",IF(INDEX('Apartment Tracker'!$G$3:$G$62,I$2)="","",INDEX('Apartment Tracker'!$G$3:$G$62,I$2)))}
A9: Maintenance (₹/month) | B9: {=IF(B$2="","",IF(INDEX('Apartment Tracker'!$H$3:$H$62,B$2)="","",INDEX('Apartment Tracker'!$H$3:$H$62,B$2)))} | C9: {=IF(C$2="","",IF(INDEX('Apartment Tracker'!$H$3:$H$62,C$2)="","",INDEX('Apartment Tracker'!$H$3:$H$62,C$2)))} | D9: {=IF(D$2="","",IF(INDEX('Apartment Tracker'!$H$3:$H$62,D$2)="","",INDEX('Apartment Tracker'!$H$3:$H$62,D$2)))} | E9: {=IF(E$2="","",IF(INDEX('Apartment Tracker'!$H$3:$H$62,E$2)="","",INDEX('Apartment Tracker'!$H$3:$H$62,E$2)))} | F9: {=IF(F$2="","",IF(INDEX('Apartment Tracker'!$H$3:$H$62,F$2)="","",INDEX('Apartment Tracker'!$H$3:$H$62,F$2)))} | G9: {=IF(G$2="","",IF(INDEX('Apartment Tracker'!$H$3:$H$62,G$2)="","",INDEX('Apartment Tracker'!$H$3:$H$62,G$2)))} | H9: {=IF(H$2="","",IF(INDEX('Apartment Tracker'!$H$3:$H$62,H$2)="","",INDEX('Apartment Tracker'!$H$3:$H$62,H$2)))} | I9: {=IF(I$2="","",IF(INDEX('Apartment Tracker'!$H$3:$H$62,I$2)="","",INDEX('Apartment Tracker'!$H$3:$H$62,I$2)))}
A10: Total monthly cost (₹) | B10: {=IF(B$2="","",IF(INDEX('Apartment Tracker'!$I$3:$I$62,B$2)="","",INDEX('Apartment Tracker'!$I$3:$I$62,B$2)))} | C10: {=IF(C$2="","",IF(INDEX('Apartment Tracker'!$I$3:$I$62,C$2)="","",INDEX('Apartment Tracker'!$I$3:$I$62,C$2)))} | D10: {=IF(D$2="","",IF(INDEX('Apartment Tracker'!$I$3:$I$62,D$2)="","",INDEX('Apartment Tracker'!$I$3:$I$62,D$2)))} | E10: {=IF(E$2="","",IF(INDEX('Apartment Tracker'!$I$3:$I$62,E$2)="","",INDEX('Apartment Tracker'!$I$3:$I$62,E$2)))} | F10: {=IF(F$2="","",IF(INDEX('Apartment Tracker'!$I$3:$I$62,F$2)="","",INDEX('Apartment Tracker'!$I$3:$I$62,F$2)))} | G10: {=IF(G$2="","",IF(INDEX('Apartment Tracker'!$I$3:$I$62,G$2)="","",INDEX('Apartment Tracker'!$I$3:$I$62,G$2)))} | H10: {=IF(H$2="","",IF(INDEX('Apartment Tracker'!$I$3:$I$62,H$2)="","",INDEX('Apartment Tracker'!$I$3:$I$62,H$2)))} | I10: {=IF(I$2="","",IF(INDEX('Apartment Tracker'!$I$3:$I$62,I$2)="","",INDEX('Apartment Tracker'!$I$3:$I$62,I$2)))}
A11: Deposit (₹) | B11: {=IF(B$2="","",IF(INDEX('Apartment Tracker'!$J$3:$J$62,B$2)="","",INDEX('Apartment Tracker'!$J$3:$J$62,B$2)))} | C11: {=IF(C$2="","",IF(INDEX('Apartment Tracker'!$J$3:$J$62,C$2)="","",INDEX('Apartment Tracker'!$J$3:$J$62,C$2)))} | D11: {=IF(D$2="","",IF(INDEX('Apartment Tracker'!$J$3:$J$62,D$2)="","",INDEX('Apartment Tracker'!$J$3:$J$62,D$2)))} | E11: {=IF(E$2="","",IF(INDEX('Apartment Tracker'!$J$3:$J$62,E$2)="","",INDEX('Apartment Tracker'!$J$3:$J$62,E$2)))} | F11: {=IF(F$2="","",IF(INDEX('Apartment Tracker'!$J$3:$J$62,F$2)="","",INDEX('Apartment Tracker'!$J$3:$J$62,F$2)))} | G11: {=IF(G$2="","",IF(INDEX('Apartment Tracker'!$J$3:$J$62,G$2)="","",INDEX('Apartment Tracker'!$J$3:$J$62,G$2)))} | H11: {=IF(H$2="","",IF(INDEX('Apartment Tracker'!$J$3:$J$62,H$2)="","",INDEX('Apartment Tracker'!$J$3:$J$62,H$2)))} | I11: {=IF(I$2="","",IF(INDEX('Apartment Tracker'!$J$3:$J$62,I$2)="","",INDEX('Apartment Tracker'!$J$3:$J$62,I$2)))}
A12: Brokerage fee (₹) | B12: {=IF(B$2="","",IF(INDEX('Apartment Tracker'!$K$3:$K$62,B$2)="","",INDEX('Apartment Tracker'!$K$3:$K$62,B$2)))} | C12: {=IF(C$2="","",IF(INDEX('Apartment Tracker'!$K$3:$K$62,C$2)="","",INDEX('Apartment Tracker'!$K$3:$K$62,C$2)))} | D12: {=IF(D$2="","",IF(INDEX('Apartment Tracker'!$K$3:$K$62,D$2)="","",INDEX('Apartment Tracker'!$K$3:$K$62,D$2)))} | E12: {=IF(E$2="","",IF(INDEX('Apartment Tracker'!$K$3:$K$62,E$2)="","",INDEX('Apartment Tracker'!$K$3:$K$62,E$2)))} | F12: {=IF(F$2="","",IF(INDEX('Apartment Tracker'!$K$3:$K$62,F$2)="","",INDEX('Apartment Tracker'!$K$3:$K$62,F$2)))} | G12: {=IF(G$2="","",IF(INDEX('Apartment Tracker'!$K$3:$K$62,G$2)="","",INDEX('Apartment Tracker'!$K$3:$K$62,G$2)))} | H12: {=IF(H$2="","",IF(INDEX('Apartment Tracker'!$K$3:$K$62,H$2)="","",INDEX('Apartment Tracker'!$K$3:$K$62,H$2)))} | I12: {=IF(I$2="","",IF(INDEX('Apartment Tracker'!$K$3:$K$62,I$2)="","",INDEX('Apartment Tracker'!$K$3:$K$62,I$2)))}
A13: Area (sq ft) | B13: {=IF(B$2="","",IF(INDEX('Apartment Tracker'!$L$3:$L$62,B$2)="","",INDEX('Apartment Tracker'!$L$3:$L$62,B$2)))} | C13: {=IF(C$2="","",IF(INDEX('Apartment Tracker'!$L$3:$L$62,C$2)="","",INDEX('Apartment Tracker'!$L$3:$L$62,C$2)))} | D13: {=IF(D$2="","",IF(INDEX('Apartment Tracker'!$L$3:$L$62,D$2)="","",INDEX('Apartment Tracker'!$L$3:$L$62,D$2)))} | E13: {=IF(E$2="","",IF(INDEX('Apartment Tracker'!$L$3:$L$62,E$2)="","",INDEX('Apartment Tracker'!$L$3:$L$62,E$2)))} | F13: {=IF(F$2="","",IF(INDEX('Apartment Tracker'!$L$3:$L$62,F$2)="","",INDEX('Apartment Tracker'!$L$3:$L$62,F$2)))} | G13: {=IF(G$2="","",IF(INDEX('Apartment Tracker'!$L$3:$L$62,G$2)="","",INDEX('Apartment Tracker'!$L$3:$L$62,G$2)))} | H13: {=IF(H$2="","",IF(INDEX('Apartment Tracker'!$L$3:$L$62,H$2)="","",INDEX('Apartment Tracker'!$L$3:$L$62,H$2)))} | I13: {=IF(I$2="","",IF(INDEX('Apartment Tracker'!$L$3:$L$62,I$2)="","",INDEX('Apartment Tracker'!$L$3:$L$62,I$2)))}
A14: Floor / total floors | B14: {=IF(B$2="","",IF(INDEX('Apartment Tracker'!$M$3:$M$62,B$2)="","",INDEX('Apartment Tracker'!$M$3:$M$62,B$2)))} | C14: {=IF(C$2="","",IF(INDEX('Apartment Tracker'!$M$3:$M$62,C$2)="","",INDEX('Apartment Tracker'!$M$3:$M$62,C$2)))} | D14: {=IF(D$2="","",IF(INDEX('Apartment Tracker'!$M$3:$M$62,D$2)="","",INDEX('Apartment Tracker'!$M$3:$M$62,D$2)))} | E14: {=IF(E$2="","",IF(INDEX('Apartment Tracker'!$M$3:$M$62,E$2)="","",INDEX('Apartment Tracker'!$M$3:$M$62,E$2)))} | F14: {=IF(F$2="","",IF(INDEX('Apartment Tracker'!$M$3:$M$62,F$2)="","",INDEX('Apartment Tracker'!$M$3:$M$62,F$2)))} | G14: {=IF(G$2="","",IF(INDEX('Apartment Tracker'!$M$3:$M$62,G$2)="","",INDEX('Apartment Tracker'!$M$3:$M$62,G$2)))} | H14: {=IF(H$2="","",IF(INDEX('Apartment Tracker'!$M$3:$M$62,H$2)="","",INDEX('Apartment Tracker'!$M$3:$M$62,H$2)))} | I14: {=IF(I$2="","",IF(INDEX('Apartment Tracker'!$M$3:$M$62,I$2)="","",INDEX('Apartment Tracker'!$M$3:$M$62,I$2)))}
A15: Furnishing | B15: {=IF(B$2="","",IF(INDEX('Apartment Tracker'!$N$3:$N$62,B$2)="","",INDEX('Apartment Tracker'!$N$3:$N$62,B$2)))} | C15: {=IF(C$2="","",IF(INDEX('Apartment Tracker'!$N$3:$N$62,C$2)="","",INDEX('Apartment Tracker'!$N$3:$N$62,C$2)))} | D15: {=IF(D$2="","",IF(INDEX('Apartment Tracker'!$N$3:$N$62,D$2)="","",INDEX('Apartment Tracker'!$N$3:$N$62,D$2)))} | E15: {=IF(E$2="","",IF(INDEX('Apartment Tracker'!$N$3:$N$62,E$2)="","",INDEX('Apartment Tracker'!$N$3:$N$62,E$2)))} | F15: {=IF(F$2="","",IF(INDEX('Apartment Tracker'!$N$3:$N$62,F$2)="","",INDEX('Apartment Tracker'!$N$3:$N$62,F$2)))} | G15: {=IF(G$2="","",IF(INDEX('Apartment Tracker'!$N$3:$N$62,G$2)="","",INDEX('Apartment Tracker'!$N$3:$N$62,G$2)))} | H15: {=IF(H$2="","",IF(INDEX('Apartment Tracker'!$N$3:$N$62,H$2)="","",INDEX('Apartment Tracker'!$N$3:$N$62,H$2)))} | I15: {=IF(I$2="","",IF(INDEX('Apartment Tracker'!$N$3:$N$62,I$2)="","",INDEX('Apartment Tracker'!$N$3:$N$62,I$2)))}
A16: Parking | B16: {=IF(B$2="","",IF(INDEX('Apartment Tracker'!$O$3:$O$62,B$2)="","",INDEX('Apartment Tracker'!$O$3:$O$62,B$2)))} | C16: {=IF(C$2="","",IF(INDEX('Apartment Tracker'!$O$3:$O$62,C$2)="","",INDEX('Apartment Tracker'!$O$3:$O$62,C$2)))} | D16: {=IF(D$2="","",IF(INDEX('Apartment Tracker'!$O$3:$O$62,D$2)="","",INDEX('Apartment Tracker'!$O$3:$O$62,D$2)))} | E16: {=IF(E$2="","",IF(INDEX('Apartment Tracker'!$O$3:$O$62,E$2)="","",INDEX('Apartment Tracker'!$O$3:$O$62,E$2)))} | F16: {=IF(F$2="","",IF(INDEX('Apartment Tracker'!$O$3:$O$62,F$2)="","",INDEX('Apartment Tracker'!$O$3:$O$62,F$2)))} | G16: {=IF(G$2="","",IF(INDEX('Apartment Tracker'!$O$3:$O$62,G$2)="","",INDEX('Apartment Tracker'!$O$3:$O$62,G$2)))} | H16: {=IF(H$2="","",IF(INDEX('Apartment Tracker'!$O$3:$O$62,H$2)="","",INDEX('Apartment Tracker'!$O$3:$O$62,H$2)))} | I16: {=IF(I$2="","",IF(INDEX('Apartment Tracker'!$O$3:$O$62,I$2)="","",INDEX('Apartment Tracker'!$O$3:$O$62,I$2)))}
A17: Lift | B17: {=IF(B$2="","",IF(INDEX('Apartment Tracker'!$P$3:$P$62,B$2)="","",INDEX('Apartment Tracker'!$P$3:$P$62,B$2)))} | C17: {=IF(C$2="","",IF(INDEX('Apartment Tracker'!$P$3:$P$62,C$2)="","",INDEX('Apartment Tracker'!$P$3:$P$62,C$2)))} | D17: {=IF(D$2="","",IF(INDEX('Apartment Tracker'!$P$3:$P$62,D$2)="","",INDEX('Apartment Tracker'!$P$3:$P$62,D$2)))} | E17: {=IF(E$2="","",IF(INDEX('Apartment Tracker'!$P$3:$P$62,E$2)="","",INDEX('Apartment Tracker'!$P$3:$P$62,E$2)))} | F17: {=IF(F$2="","",IF(INDEX('Apartment Tracker'!$P$3:$P$62,F$2)="","",INDEX('Apartment Tracker'!$P$3:$P$62,F$2)))} | G17: {=IF(G$2="","",IF(INDEX('Apartment Tracker'!$P$3:$P$62,G$2)="","",INDEX('Apartment Tracker'!$P$3:$P$62,G$2)))} | H17: {=IF(H$2="","",IF(INDEX('Apartment Tracker'!$P$3:$P$62,H$2)="","",INDEX('Apartment Tracker'!$P$3:$P$62,H$2)))} | I17: {=IF(I$2="","",IF(INDEX('Apartment Tracker'!$P$3:$P$62,I$2)="","",INDEX('Apartment Tracker'!$P$3:$P$62,I$2)))}
A18: Available from | B18: {=IF(B$2="","",IF(INDEX('Apartment Tracker'!$Q$3:$Q$62,B$2)="","",INDEX('Apartment Tracker'!$Q$3:$Q$62,B$2)))} | C18: {=IF(C$2="","",IF(INDEX('Apartment Tracker'!$Q$3:$Q$62,C$2)="","",INDEX('Apartment Tracker'!$Q$3:$Q$62,C$2)))} | D18: {=IF(D$2="","",IF(INDEX('Apartment Tracker'!$Q$3:$Q$62,D$2)="","",INDEX('Apartment Tracker'!$Q$3:$Q$62,D$2)))} | E18: {=IF(E$2="","",IF(INDEX('Apartment Tracker'!$Q$3:$Q$62,E$2)="","",INDEX('Apartment Tracker'!$Q$3:$Q$62,E$2)))} | F18: {=IF(F$2="","",IF(INDEX('Apartment Tracker'!$Q$3:$Q$62,F$2)="","",INDEX('Apartment Tracker'!$Q$3:$Q$62,F$2)))} | G18: {=IF(G$2="","",IF(INDEX('Apartment Tracker'!$Q$3:$Q$62,G$2)="","",INDEX('Apartment Tracker'!$Q$3:$Q$62,G$2)))} | H18: {=IF(H$2="","",IF(INDEX('Apartment Tracker'!$Q$3:$Q$62,H$2)="","",INDEX('Apartment Tracker'!$Q$3:$Q$62,H$2)))} | I18: {=IF(I$2="","",IF(INDEX('Apartment Tracker'!$Q$3:$Q$62,I$2)="","",INDEX('Apartment Tracker'!$Q$3:$Q$62,I$2)))}
A19: Distance from workplace (km) | B19: {=IF(B$2="","",IF(INDEX('Apartment Tracker'!$R$3:$R$62,B$2)="","",INDEX('Apartment Tracker'!$R$3:$R$62,B$2)))} | C19: {=IF(C$2="","",IF(INDEX('Apartment Tracker'!$R$3:$R$62,C$2)="","",INDEX('Apartment Tracker'!$R$3:$R$62,C$2)))} | D19: {=IF(D$2="","",IF(INDEX('Apartment Tracker'!$R$3:$R$62,D$2)="","",INDEX('Apartment Tracker'!$R$3:$R$62,D$2)))} | E19: {=IF(E$2="","",IF(INDEX('Apartment Tracker'!$R$3:$R$62,E$2)="","",INDEX('Apartment Tracker'!$R$3:$R$62,E$2)))} | F19: {=IF(F$2="","",IF(INDEX('Apartment Tracker'!$R$3:$R$62,F$2)="","",INDEX('Apartment Tracker'!$R$3:$R$62,F$2)))} | G19: {=IF(G$2="","",IF(INDEX('Apartment Tracker'!$R$3:$R$62,G$2)="","",INDEX('Apartment Tracker'!$R$3:$R$62,G$2)))} | H19: {=IF(H$2="","",IF(INDEX('Apartment Tracker'!$R$3:$R$62,H$2)="","",INDEX('Apartment Tracker'!$R$3:$R$62,H$2)))} | I19: {=IF(I$2="","",IF(INDEX('Apartment Tracker'!$R$3:$R$62,I$2)="","",INDEX('Apartment Tracker'!$R$3:$R$62,I$2)))}
A20: Safety (1-5) | B20: {=IF(B$2="","",IF(INDEX('Apartment Tracker'!$S$3:$S$62,B$2)="","",INDEX('Apartment Tracker'!$S$3:$S$62,B$2)))} | C20: {=IF(C$2="","",IF(INDEX('Apartment Tracker'!$S$3:$S$62,C$2)="","",INDEX('Apartment Tracker'!$S$3:$S$62,C$2)))} | D20: {=IF(D$2="","",IF(INDEX('Apartment Tracker'!$S$3:$S$62,D$2)="","",INDEX('Apartment Tracker'!$S$3:$S$62,D$2)))} | E20: {=IF(E$2="","",IF(INDEX('Apartment Tracker'!$S$3:$S$62,E$2)="","",INDEX('Apartment Tracker'!$S$3:$S$62,E$2)))} | F20: {=IF(F$2="","",IF(INDEX('Apartment Tracker'!$S$3:$S$62,F$2)="","",INDEX('Apartment Tracker'!$S$3:$S$62,F$2)))} | G20: {=IF(G$2="","",IF(INDEX('Apartment Tracker'!$S$3:$S$62,G$2)="","",INDEX('Apartment Tracker'!$S$3:$S$62,G$2)))} | H20: {=IF(H$2="","",IF(INDEX('Apartment Tracker'!$S$3:$S$62,H$2)="","",INDEX('Apartment Tracker'!$S$3:$S$62,H$2)))} | I20: {=IF(I$2="","",IF(INDEX('Apartment Tracker'!$S$3:$S$62,I$2)="","",INDEX('Apartment Tracker'!$S$3:$S$62,I$2)))}
A21: Water supply (1-5) | B21: {=IF(B$2="","",IF(INDEX('Apartment Tracker'!$T$3:$T$62,B$2)="","",INDEX('Apartment Tracker'!$T$3:$T$62,B$2)))} | C21: {=IF(C$2="","",IF(INDEX('Apartment Tracker'!$T$3:$T$62,C$2)="","",INDEX('Apartment Tracker'!$T$3:$T$62,C$2)))} | D21: {=IF(D$2="","",IF(INDEX('Apartment Tracker'!$T$3:$T$62,D$2)="","",INDEX('Apartment Tracker'!$T$3:$T$62,D$2)))} | E21: {=IF(E$2="","",IF(INDEX('Apartment Tracker'!$T$3:$T$62,E$2)="","",INDEX('Apartment Tracker'!$T$3:$T$62,E$2)))} | F21: {=IF(F$2="","",IF(INDEX('Apartment Tracker'!$T$3:$T$62,F$2)="","",INDEX('Apartment Tracker'!$T$3:$T$62,F$2)))} | G21: {=IF(G$2="","",IF(INDEX('Apartment Tracker'!$T$3:$T$62,G$2)="","",INDEX('Apartment Tracker'!$T$3:$T$62,G$2)))} | H21: {=IF(H$2="","",IF(INDEX('Apartment Tracker'!$T$3:$T$62,H$2)="","",INDEX('Apartment Tracker'!$T$3:$T$62,H$2)))} | I21: {=IF(I$2="","",IF(INDEX('Apartment Tracker'!$T$3:$T$62,I$2)="","",INDEX('Apartment Tracker'!$T$3:$T$62,I$2)))}
A22: Location (1-5) | B22: {=IF(B$2="","",IF(INDEX('Apartment Tracker'!$U$3:$U$62,B$2)="","",INDEX('Apartment Tracker'!$U$3:$U$62,B$2)))} | C22: {=IF(C$2="","",IF(INDEX('Apartment Tracker'!$U$3:$U$62,C$2)="","",INDEX('Apartment Tracker'!$U$3:$U$62,C$2)))} | D22: {=IF(D$2="","",IF(INDEX('Apartment Tracker'!$U$3:$U$62,D$2)="","",INDEX('Apartment Tracker'!$U$3:$U$62,D$2)))} | E22: {=IF(E$2="","",IF(INDEX('Apartment Tracker'!$U$3:$U$62,E$2)="","",INDEX('Apartment Tracker'!$U$3:$U$62,E$2)))} | F22: {=IF(F$2="","",IF(INDEX('Apartment Tracker'!$U$3:$U$62,F$2)="","",INDEX('Apartment Tracker'!$U$3:$U$62,F$2)))} | G22: {=IF(G$2="","",IF(INDEX('Apartment Tracker'!$U$3:$U$62,G$2)="","",INDEX('Apartment Tracker'!$U$3:$U$62,G$2)))} | H22: {=IF(H$2="","",IF(INDEX('Apartment Tracker'!$U$3:$U$62,H$2)="","",INDEX('Apartment Tracker'!$U$3:$U$62,H$2)))} | I22: {=IF(I$2="","",IF(INDEX('Apartment Tracker'!$U$3:$U$62,I$2)="","",INDEX('Apartment Tracker'!$U$3:$U$62,I$2)))}
A23: Condition (1-5) | B23: {=IF(B$2="","",IF(INDEX('Apartment Tracker'!$V$3:$V$62,B$2)="","",INDEX('Apartment Tracker'!$V$3:$V$62,B$2)))} | C23: {=IF(C$2="","",IF(INDEX('Apartment Tracker'!$V$3:$V$62,C$2)="","",INDEX('Apartment Tracker'!$V$3:$V$62,C$2)))} | D23: {=IF(D$2="","",IF(INDEX('Apartment Tracker'!$V$3:$V$62,D$2)="","",INDEX('Apartment Tracker'!$V$3:$V$62,D$2)))} | E23: {=IF(E$2="","",IF(INDEX('Apartment Tracker'!$V$3:$V$62,E$2)="","",INDEX('Apartment Tracker'!$V$3:$V$62,E$2)))} | F23: {=IF(F$2="","",IF(INDEX('Apartment Tracker'!$V$3:$V$62,F$2)="","",INDEX('Apartment Tracker'!$V$3:$V$62,F$2)))} | G23: {=IF(G$2="","",IF(INDEX('Apartment Tracker'!$V$3:$V$62,G$2)="","",INDEX('Apartment Tracker'!$V$3:$V$62,G$2)))} | H23: {=IF(H$2="","",IF(INDEX('Apartment Tracker'!$V$3:$V$62,H$2)="","",INDEX('Apartment Tracker'!$V$3:$V$62,H$2)))} | I23: {=IF(I$2="","",IF(INDEX('Apartment Tracker'!$V$3:$V$62,I$2)="","",INDEX('Apartment Tracker'!$V$3:$V$62,I$2)))}
A24: Natural light (1-5) | B24: {=IF(B$2="","",IF(INDEX('Apartment Tracker'!$W$3:$W$62,B$2)="","",INDEX('Apartment Tracker'!$W$3:$W$62,B$2)))} | C24: {=IF(C$2="","",IF(INDEX('Apartment Tracker'!$W$3:$W$62,C$2)="","",INDEX('Apartment Tracker'!$W$3:$W$62,C$2)))} | D24: {=IF(D$2="","",IF(INDEX('Apartment Tracker'!$W$3:$W$62,D$2)="","",INDEX('Apartment Tracker'!$W$3:$W$62,D$2)))} | E24: {=IF(E$2="","",IF(INDEX('Apartment Tracker'!$W$3:$W$62,E$2)="","",INDEX('Apartment Tracker'!$W$3:$W$62,E$2)))} | F24: {=IF(F$2="","",IF(INDEX('Apartment Tracker'!$W$3:$W$62,F$2)="","",INDEX('Apartment Tracker'!$W$3:$W$62,F$2)))} | G24: {=IF(G$2="","",IF(INDEX('Apartment Tracker'!$W$3:$W$62,G$2)="","",INDEX('Apartment Tracker'!$W$3:$W$62,G$2)))} | H24: {=IF(H$2="","",IF(INDEX('Apartment Tracker'!$W$3:$W$62,H$2)="","",INDEX('Apartment Tracker'!$W$3:$W$62,H$2)))} | I24: {=IF(I$2="","",IF(INDEX('Apartment Tracker'!$W$3:$W$62,I$2)="","",INDEX('Apartment Tracker'!$W$3:$W$62,I$2)))}
A25: Overall rating (1-5) | B25: {=IF(B$2="","",IF(INDEX('Apartment Tracker'!$X$3:$X$62,B$2)="","",INDEX('Apartment Tracker'!$X$3:$X$62,B$2)))} | C25: {=IF(C$2="","",IF(INDEX('Apartment Tracker'!$X$3:$X$62,C$2)="","",INDEX('Apartment Tracker'!$X$3:$X$62,C$2)))} | D25: {=IF(D$2="","",IF(INDEX('Apartment Tracker'!$X$3:$X$62,D$2)="","",INDEX('Apartment Tracker'!$X$3:$X$62,D$2)))} | E25: {=IF(E$2="","",IF(INDEX('Apartment Tracker'!$X$3:$X$62,E$2)="","",INDEX('Apartment Tracker'!$X$3:$X$62,E$2)))} | F25: {=IF(F$2="","",IF(INDEX('Apartment Tracker'!$X$3:$X$62,F$2)="","",INDEX('Apartment Tracker'!$X$3:$X$62,F$2)))} | G25: {=IF(G$2="","",IF(INDEX('Apartment Tracker'!$X$3:$X$62,G$2)="","",INDEX('Apartment Tracker'!$X$3:$X$62,G$2)))} | H25: {=IF(H$2="","",IF(INDEX('Apartment Tracker'!$X$3:$X$62,H$2)="","",INDEX('Apartment Tracker'!$X$3:$X$62,H$2)))} | I25: {=IF(I$2="","",IF(INDEX('Apartment Tracker'!$X$3:$X$62,I$2)="","",INDEX('Apartment Tracker'!$X$3:$X$62,I$2)))}
A26: Pros | B26: {=IF(B$2="","",IF(INDEX('Apartment Tracker'!$Y$3:$Y$62,B$2)="","",INDEX('Apartment Tracker'!$Y$3:$Y$62,B$2)))} | C26: {=IF(C$2="","",IF(INDEX('Apartment Tracker'!$Y$3:$Y$62,C$2)="","",INDEX('Apartment Tracker'!$Y$3:$Y$62,C$2)))} | D26: {=IF(D$2="","",IF(INDEX('Apartment Tracker'!$Y$3:$Y$62,D$2)="","",INDEX('Apartment Tracker'!$Y$3:$Y$62,D$2)))} | E26: {=IF(E$2="","",IF(INDEX('Apartment Tracker'!$Y$3:$Y$62,E$2)="","",INDEX('Apartment Tracker'!$Y$3:$Y$62,E$2)))} | F26: {=IF(F$2="","",IF(INDEX('Apartment Tracker'!$Y$3:$Y$62,F$2)="","",INDEX('Apartment Tracker'!$Y$3:$Y$62,F$2)))} | G26: {=IF(G$2="","",IF(INDEX('Apartment Tracker'!$Y$3:$Y$62,G$2)="","",INDEX('Apartment Tracker'!$Y$3:$Y$62,G$2)))} | H26: {=IF(H$2="","",IF(INDEX('Apartment Tracker'!$Y$3:$Y$62,H$2)="","",INDEX('Apartment Tracker'!$Y$3:$Y$62,H$2)))} | I26: {=IF(I$2="","",IF(INDEX('Apartment Tracker'!$Y$3:$Y$62,I$2)="","",INDEX('Apartment Tracker'!$Y$3:$Y$62,I$2)))}
A27: Cons | B27: {=IF(B$2="","",IF(INDEX('Apartment Tracker'!$Z$3:$Z$62,B$2)="","",INDEX('Apartment Tracker'!$Z$3:$Z$62,B$2)))} | C27: {=IF(C$2="","",IF(INDEX('Apartment Tracker'!$Z$3:$Z$62,C$2)="","",INDEX('Apartment Tracker'!$Z$3:$Z$62,C$2)))} | D27: {=IF(D$2="","",IF(INDEX('Apartment Tracker'!$Z$3:$Z$62,D$2)="","",INDEX('Apartment Tracker'!$Z$3:$Z$62,D$2)))} | E27: {=IF(E$2="","",IF(INDEX('Apartment Tracker'!$Z$3:$Z$62,E$2)="","",INDEX('Apartment Tracker'!$Z$3:$Z$62,E$2)))} | F27: {=IF(F$2="","",IF(INDEX('Apartment Tracker'!$Z$3:$Z$62,F$2)="","",INDEX('Apartment Tracker'!$Z$3:$Z$62,F$2)))} | G27: {=IF(G$2="","",IF(INDEX('Apartment Tracker'!$Z$3:$Z$62,G$2)="","",INDEX('Apartment Tracker'!$Z$3:$Z$62,G$2)))} | H27: {=IF(H$2="","",IF(INDEX('Apartment Tracker'!$Z$3:$Z$62,H$2)="","",INDEX('Apartment Tracker'!$Z$3:$Z$62,H$2)))} | I27: {=IF(I$2="","",IF(INDEX('Apartment Tracker'!$Z$3:$Z$62,I$2)="","",INDEX('Apartment Tracker'!$Z$3:$Z$62,I$2)))}
A28: Photos link | B28: {=IF(B$2="","",IF(INDEX('Apartment Tracker'!$AA$3:$AA$62,B$2)="","",INDEX('Apartment Tracker'!$AA$3:$AA$62,B$2)))} | C28: {=IF(C$2="","",IF(INDEX('Apartment Tracker'!$AA$3:$AA$62,C$2)="","",INDEX('Apartment Tracker'!$AA$3:$AA$62,C$2)))} | D28: {=IF(D$2="","",IF(INDEX('Apartment Tracker'!$AA$3:$AA$62,D$2)="","",INDEX('Apartment Tracker'!$AA$3:$AA$62,D$2)))} | E28: {=IF(E$2="","",IF(INDEX('Apartment Tracker'!$AA$3:$AA$62,E$2)="","",INDEX('Apartment Tracker'!$AA$3:$AA$62,E$2)))} | F28: {=IF(F$2="","",IF(INDEX('Apartment Tracker'!$AA$3:$AA$62,F$2)="","",INDEX('Apartment Tracker'!$AA$3:$AA$62,F$2)))} | G28: {=IF(G$2="","",IF(INDEX('Apartment Tracker'!$AA$3:$AA$62,G$2)="","",INDEX('Apartment Tracker'!$AA$3:$AA$62,G$2)))} | H28: {=IF(H$2="","",IF(INDEX('Apartment Tracker'!$AA$3:$AA$62,H$2)="","",INDEX('Apartment Tracker'!$AA$3:$AA$62,H$2)))} | I28: {=IF(I$2="","",IF(INDEX('Apartment Tracker'!$AA$3:$AA$62,I$2)="","",INDEX('Apartment Tracker'!$AA$3:$AA$62,I$2)))}
A30: Shows every apartment with Status set to Shortlisted in the tracker, in tracker order. Space for 8.
